{
    "matches": [
        {
            "matchTime": "2024-04-24T02:00:00.000+08:00",
            "frontEndId": "FB5304",
            "homeTeam": {
                "teamNameCH": "希拉爾",
                "teamNameEN": "Al Hilal"
            },
            "awayTeam": {
                "teamNameCH": "艾阿恩",
                "teamNameEN": "Al Ain"
            },
            "isESOffer": true,
            "tournament": {
                "tournamentNameCH": "亞洲聯賽冠軍盃",
                "tournamentNameEN": "Asian Champions League"
            },
            "liveEvent": {
                "hasLiveInfo": true
            },
            "anyInplaySelling": "1"
        },
        {
            "matchTime": "2024-04-24T02:30:00.000+08:00",
            "frontEndId": "FB5324",
            "homeTeam": {
                "teamNameCH": "標準列治",
                "teamNameEN": "Standard"
            },
            "awayTeam": {
                "teamNameCH": "梅赫倫",
                "teamNameEN": "KV Mechelen"
            },
            "isESOffer": true,
            "tournament": {
                "tournamentNameCH": "比利時甲組聯賽",
                "tournamentNameEN": "Belgian Division 1"
            },
            "liveEvent": {
                "hasLiveInfo": true
            },
            "anyInplaySelling": "-1"
        },
        {
            "matchTime": "2024-04-24T02:30:00.000+08:00",
            "frontEndId": "FB5323",
            "homeTeam": {
                "teamNameCH": "聖圖爾登",
                "teamNameEN": "Sint Truiden"
            },
            "awayTeam": {
                "teamNameCH": "真特",
                "teamNameEN": "AA Gent"
            },
            "isESOffer": true,
            "tournament": {
                "tournamentNameCH": "比利時甲組聯賽",
                "tournamentNameEN": "Belgian Division 1"
            },
            "liveEvent": {
                "hasLiveInfo": true
            },
            "anyInplaySelling": "-1"
        },
        {
            "matchTime": "2024-04-24T02:30:00.000+08:00",
            "frontEndId": "FB5327",
            "homeTeam": {
                "teamNameCH": "韋斯達路",
                "teamNameEN": "Westerlo"
            },
            "awayTeam": {
                "teamNameCH": "奧特海維利",
                "teamNameEN": "OH Leuven"
            },
            "isESOffer": true,
            "tournament": {
                "tournamentNameCH": "比利時甲組聯賽",
                "tournamentNameEN": "Belgian Division 1"
            },
            "liveEvent": {
                "hasLiveInfo": true
            },
            "anyInplaySelling": "-1"
        },
        {
            "matchTime": "2024-04-24T02:45:00.000+08:00",
            "frontEndId": "FB5355",
            "homeTeam": {
                "teamNameCH": "劍橋聯",
                "teamNameEN": "Cambridge Utd"
            },
            "awayTeam": {
                "teamNameCH": "韋甘比",
                "teamNameEN": "Wycombe"
            },
            "isESOffer": true,
            "tournament": {
                "tournamentNameCH": "英格蘭甲組聯賽",
                "tournamentNameEN": "Eng League 1"
            },
            "liveEvent": {
                "hasLiveInfo": false
            },
            "anyInplaySelling": "1"
        },
        {
            "matchTime": "2024-04-24T02:45:00.000+08:00",
            "frontEndId": "FB5357",
            "homeTeam": {
                "teamNameCH": "車頓咸",
                "teamNameEN": "Cheltenham"
            },
            "awayTeam": {
                "teamNameCH": "彼德堡",
                "teamNameEN": "Peterborough"
            },
            "isESOffer": true,
            "tournament": {
                "tournamentNameCH": "英格蘭甲組聯賽",
                "tournamentNameEN": "Eng League 1"
            },
            "liveEvent": {
                "hasLiveInfo": false
            },
            "anyInplaySelling": "1"
        },
        {
            "matchTime": "2024-04-24T02:45:00.000+08:00",
            "frontEndId": "FB5337",
            "homeTeam": {
                "teamNameCH": "歐塞爾",
                "teamNameEN": "Auxerre"
            },
            "awayTeam": {
                "teamNameCH": "拉瓦勒",
                "teamNameEN": "Laval"
            },
            "isESOffer": true,
            "tournament": {
                "tournamentNameCH": "法國乙組聯賽",
                "tournamentNameEN": "French Division 2"
            },
            "liveEvent": {
                "hasLiveInfo": true
            },
            "anyInplaySelling": "-1"
        },
        {
            "matchTime": "2024-04-24T02:45:00.000+08:00",
            "frontEndId": "FB5338",
            "homeTeam": {
                "teamNameCH": "巴斯蒂亞",
                "teamNameEN": "Bastia"
            },
            "awayTeam": {
                "teamNameCH": "干卡紐",
                "teamNameEN": "Concarneau"
            },
            "isESOffer": true,
            "tournament": {
                "tournamentNameCH": "法國乙組聯賽",
                "tournamentNameEN": "French Division 2"
            },
            "liveEvent": {
                "hasLiveInfo": true
            },
            "anyInplaySelling": "-1"
        },
        {
            "matchTime": "2024-04-24T02:45:00.000+08:00",
            "frontEndId": "FB5335",
            "homeTeam": {
                "teamNameCH": "波爾多",
                "teamNameEN": "Bordeaux"
            },
            "awayTeam": {
                "teamNameCH": "登卡基",
                "teamNameEN": "Dunkerque"
            },
            "isESOffer": true,
            "tournament": {
                "tournamentNameCH": "法國乙組聯賽",
                "tournamentNameEN": "French Division 2"
            },
            "liveEvent": {
                "hasLiveInfo": true
            },
            "anyInplaySelling": "-1"
        },
        {
            "matchTime": "2024-04-24T02:45:00.000+08:00",
            "frontEndId": "FB5336",
            "homeTeam": {
                "teamNameCH": "卡昂",
                "teamNameEN": "Caen"
            },
            "awayTeam": {
                "teamNameCH": "FC安納西",
                "teamNameEN": "Annecy FC"
            },
            "isESOffer": true,
            "tournament": {
                "tournamentNameCH": "法國乙組聯賽",
                "tournamentNameEN": "French Division 2"
            },
            "liveEvent": {
                "hasLiveInfo": true
            },
            "anyInplaySelling": "-1"
        },
        {
            "matchTime": "2024-04-24T02:45:00.000+08:00",
            "frontEndId": "FB5315",
            "homeTeam": {
                "teamNameCH": "格勒諾布爾",
                "teamNameEN": "Grenoble Foot"
            },
            "awayTeam": {
                "teamNameCH": "聖伊天",
                "teamNameEN": "St. Etienne"
            },
            "isESOffer": true,
            "tournament": {
                "tournamentNameCH": "法國乙組聯賽",
                "tournamentNameEN": "French Division 2"
            },
            "liveEvent": {
                "hasLiveInfo": true
            },
            "anyInplaySelling": "-1"
        },
        {
            "matchTime": "2024-04-24T02:45:00.000+08:00",
            "frontEndId": "FB5339",
            "homeTeam": {
                "teamNameCH": "甘岡",
                "teamNameEN": "Guingamp"
            },
            "awayTeam": {
                "teamNameCH": "昂熱",
                "teamNameEN": "Angers SCO"
            },
            "isESOffer": true,
            "tournament": {
                "tournamentNameCH": "法國乙組聯賽",
                "tournamentNameEN": "French Division 2"
            },
            "liveEvent": {
                "hasLiveInfo": true
            },
            "anyInplaySelling": "-1"
        },
        {
            "matchTime": "2024-04-24T02:45:00.000+08:00",
            "frontEndId": "FB5340",
            "homeTeam": {
                "teamNameCH": "羅德茲",
                "teamNameEN": "Rodez"
            },
            "awayTeam": {
                "teamNameCH": "巴黎FC",
                "teamNameEN": "Paris FC"
            },
            "isESOffer": true,
            "tournament": {
                "tournamentNameCH": "法國乙組聯賽",
                "tournamentNameEN": "French Division 2"
            },
            "liveEvent": {
                "hasLiveInfo": true
            },
            "anyInplaySelling": "-1"
        },
        {
            "matchTime": "2024-04-24T02:45:00.000+08:00",
            "frontEndId": "FB5341",
            "homeTeam": {
                "teamNameCH": "特魯瓦",
                "teamNameEN": "Troyes"
            },
            "awayTeam": {
                "teamNameCH": "FC波城",
                "teamNameEN": "Pau FC"
            },
            "isESOffer": true,
            "tournament": {
                "tournamentNameCH": "法國乙組聯賽",
                "tournamentNameEN": "French Division 2"
            },
            "liveEvent": {
                "hasLiveInfo": true
            },
            "anyInplaySelling": "-1"
        },
        {
            "matchTime": "2024-04-24T02:45:00.000+08:00",
            "frontEndId": "FB5347",
            "homeTeam": {
                "teamNameCH": "奎維利魯昂",
                "teamNameEN": "US Quevilly Rouen"
            },
            "awayTeam": {
                "teamNameCH": "艾米恩斯",
                "teamNameEN": "Amiens"
            },
            "isESOffer": true,
            "tournament": {
                "tournamentNameCH": "法國乙組聯賽",
                "tournamentNameEN": "French Division 2"
            },
            "liveEvent": {
                "hasLiveInfo": true
            },
            "anyInplaySelling": "-1"
        },
        {
            "matchTime": "2024-04-24T02:45:00.000+08:00",
            "frontEndId": "FB5370",
            "homeTeam": {
                "teamNameCH": "華倫西恩斯",
                "teamNameEN": "Valenciennes"
            },
            "awayTeam": {
                "teamNameCH": "阿些斯奧",
                "teamNameEN": "AC Ajaccio"
            },
            "isESOffer": true,
            "tournament": {
                "tournamentNameCH": "法國乙組聯賽",
                "tournamentNameEN": "French Division 2"
            },
            "liveEvent": {
                "hasLiveInfo": true
            },
            "anyInplaySelling": "-1"
        },
        {
            "matchTime": "2024-04-24T02:45:00.000+08:00",
            "frontEndId": "FB5356",
            "homeTeam": {
                "teamNameCH": "巴羅",
                "teamNameEN": "Barrow"
            },
            "awayTeam": {
                "teamNameCH": "巴拉福特",
                "teamNameEN": "Bradford"
            },
            "isESOffer": true,
            "tournament": {
                "tournamentNameCH": "英格蘭乙組聯賽",
                "tournamentNameEN": "Eng League 2"
            },
            "liveEvent": {
                "hasLiveInfo": false
            },
            "anyInplaySelling": "-1"
        },
        {
            "matchTime": "2024-04-24T02:45:00.000+08:00",
            "frontEndId": "FB5353",
            "homeTeam": {
                "teamNameCH": "高車士打",
                "teamNameEN": "Colchester"
            },
            "awayTeam": {
                "teamNameCH": "唐卡士打",
                "teamNameEN": "Doncaster"
            },
            "isESOffer": true,
            "tournament": {
                "tournamentNameCH": "英格蘭乙組聯賽",
                "tournamentNameEN": "Eng League 2"
            },
            "liveEvent": {
                "hasLiveInfo": false
            },
            "anyInplaySelling": "-1"
        },
        {
            "matchTime": "2024-04-24T03:00:00.000+08:00",
            "frontEndId": "FB5303",
            "homeTeam": {
                "teamNameCH": "阿仙奴",
                "teamNameEN": "Arsenal"
            },
            "awayTeam": {
                "teamNameCH": "車路士",
                "teamNameEN": "Chelsea"
            },
            "isESOffer": true,
            "tournament": {
                "tournamentNameCH": "英格蘭超級聯賽",
                "tournamentNameEN": "Eng Premier"
            },
            "liveEvent": {
                "hasLiveInfo": true
            },
            "anyInplaySelling": "1"
        },
        {
            "matchTime": "2024-04-24T03:00:00.000+08:00",
            "frontEndId": "FB5305",
            "homeTeam": {
                "teamNameCH": "拉素",
                "teamNameEN": "Lazio"
            },
            "awayTeam": {
                "teamNameCH": "祖雲達斯",
                "teamNameEN": "Juventus"
            },
            "isESOffer": true,
            "tournament": {
                "tournamentNameCH": "意大利盃",
                "tournamentNameEN": "Italian Cup"
            },
            "liveEvent": {
                "hasLiveInfo": true
            },
            "anyInplaySelling": "1"
        },
        {
            "matchTime": "2024-04-24T03:00:00.000+08:00",
            "frontEndId": "FB5354",
            "homeTeam": {
                "teamNameCH": "李斯特城",
                "teamNameEN": "Leicester"
            },
            "awayTeam": {
                "teamNameCH": "修咸頓",
                "teamNameEN": "Southampton"
            },
            "isESOffer": true,
            "tournament": {
                "tournamentNameCH": "英格蘭冠軍聯賽",
                "tournamentNameEN": "Eng Championship"
            },
            "liveEvent": {
                "hasLiveInfo": true
            },
            "anyInplaySelling": "1"
        },
        {
            "matchTime": "2024-04-24T05:00:00.000+08:00",
            "frontEndId": "FB5391",
            "homeTeam": {
                "teamNameCH": "阿根廷女足U20",
                "teamNameEN": "Argentina Women U20"
            },
            "awayTeam": {
                "teamNameCH": "巴西女足U20",
                "teamNameEN": "Brazil Women U20"
            },
            "isESOffer": true,
            "tournament": {
                "tournamentNameCH": "國際賽",
                "tournamentNameEN": "International Matches"
            },
            "liveEvent": {
                "hasLiveInfo": false
            },
            "anyInplaySelling": "-1"
        },
        {
            "matchTime": "2024-04-24T06:00:00.000+08:00",
            "frontEndId": "FB5358",
            "homeTeam": {
                "teamNameCH": "卡拉卡斯",
                "teamNameEN": "Caracas FC"
            },
            "awayTeam": {
                "teamNameCH": "羅沙里奧中央",
                "teamNameEN": "Rosario Central"
            },
            "isESOffer": true,
            "tournament": {
                "tournamentNameCH": "南美自由盃",
                "tournamentNameEN": "Copa Libertadores"
            },
            "liveEvent": {
                "hasLiveInfo": true
            },
            "anyInplaySelling": "1"
        },
        {
            "matchTime": "2024-04-24T06:00:00.000+08:00",
            "frontEndId": "FB5362",
            "homeTeam": {
                "teamNameCH": "學生隊",
                "teamNameEN": "Estudiantes"
            },
            "awayTeam": {
                "teamNameCH": "甘美奧",
                "teamNameEN": "Gremio"
            },
            "isESOffer": true,
            "tournament": {
                "tournamentNameCH": "南美自由盃",
                "tournamentNameEN": "Copa Libertadores"
            },
            "liveEvent": {
                "hasLiveInfo": true
            },
            "anyInplaySelling": "-1"
        },
        {
            "matchTime": "2024-04-24T06:00:00.000+08:00",
            "frontEndId": "FB5351",
            "homeTeam": {
                "teamNameCH": "卡拉雷聯",
                "teamNameEN": "Union La Calera"
            },
            "awayTeam": {
                "teamNameCH": "高士路",
                "teamNameEN": "Cruzeiro"
            },
            "isESOffer": true,
            "tournament": {
                "tournamentNameCH": "南美球會盃",
                "tournamentNameEN": "South American Cup"
            },
            "liveEvent": {
                "hasLiveInfo": true
            },
            "anyInplaySelling": "1"
        },
        {
            "matchTime": "2024-04-24T07:30:00.000+08:00",
            "frontEndId": "FB5392",
            "homeTeam": {
                "teamNameCH": "巴拉圭女足U20",
                "teamNameEN": "Paraguay Women U20"
            },
            "awayTeam": {
                "teamNameCH": "委內瑞拉女足U20",
                "teamNameEN": "Venezuela Women U20"
            },
            "isESOffer": true,
            "tournament": {
                "tournamentNameCH": "國際賽",
                "tournamentNameEN": "International Matches"
            },
            "liveEvent": {
                "hasLiveInfo": false
            },
            "anyInplaySelling": "-1"
        },
        {
            "matchTime": "2024-04-24T08:00:00.000+08:00",
            "frontEndId": "FB5331",
            "homeTeam": {
                "teamNameCH": "明尼路",
                "teamNameEN": "Atletico Mineiro"
            },
            "awayTeam": {
                "teamNameCH": "彭拿路",
                "teamNameEN": "Penarol"
            },
            "isESOffer": true,
            "tournament": {
                "tournamentNameCH": "南美自由盃",
                "tournamentNameEN": "Copa Libertadores"
            },
            "liveEvent": {
                "hasLiveInfo": true
            },
            "anyInplaySelling": "1"
        },
        {
            "matchTime": "2024-04-24T08:00:00.000+08:00",
            "frontEndId": "FB5361",
            "homeTeam": {
                "teamNameCH": "蒙特維多利物浦",
                "teamNameEN": "Montevideo Liverpool"
            },
            "awayTeam": {
                "teamNameCH": "聖羅倫素",
                "teamNameEN": "San Lorenzo"
            },
            "isESOffer": true,
            "tournament": {
                "tournamentNameCH": "南美自由盃",
                "tournamentNameEN": "Copa Libertadores"
            },
            "liveEvent": {
                "hasLiveInfo": true
            },
            "anyInplaySelling": "-1"
        },
        {
            "matchTime": "2024-04-24T08:00:00.000+08:00",
            "frontEndId": "FB5307",
            "homeTeam": {
                "teamNameCH": "加西拉索",
                "teamNameEN": "Deportivo Garcilaso"
            },
            "awayTeam": {
                "teamNameCH": "古亞巴",
                "teamNameEN": "Cuiaba"
            },
            "isESOffer": true,
            "tournament": {
                "tournamentNameCH": "南美球會盃",
                "tournamentNameEN": "South American Cup"
            },
            "liveEvent": {
                "hasLiveInfo": true
            },
            "anyInplaySelling": "-1"
        },
        {
            "matchTime": "2024-04-24T08:00:00.000+08:00",
            "frontEndId": "FB5349",
            "homeTeam": {
                "teamNameCH": "特立尼登斯",
                "teamNameEN": "Sportivo Trinidense"
            },
            "awayTeam": {
                "teamNameCH": "國民普托斯",
                "teamNameEN": "Nacional Potosi"
            },
            "isESOffer": true,
            "tournament": {
                "tournamentNameCH": "南美球會盃",
                "tournamentNameEN": "South American Cup"
            },
            "liveEvent": {
                "hasLiveInfo": true
            },
            "anyInplaySelling": "-1"
        },
        {
            "matchTime": "2024-04-24T08:30:00.000+08:00",
            "frontEndId": "FB5333",
            "homeTeam": {
                "teamNameCH": "高路高路",
                "teamNameEN": "Colo Colo"
            },
            "awayTeam": {
                "teamNameCH": "利馬聯",
                "teamNameEN": "Alianza Lima"
            },
            "isESOffer": true,
            "tournament": {
                "tournamentNameCH": "南美自由盃",
                "tournamentNameEN": "Copa Libertadores"
            },
            "liveEvent": {
                "hasLiveInfo": true
            },
            "anyInplaySelling": "-1"
        },
        {
            "matchTime": "2024-04-24T08:30:00.000+08:00",
            "frontEndId": "FB5350",
            "homeTeam": {
                "teamNameCH": "小阿根廷人",
                "teamNameEN": "Argentinos Juniors"
            },
            "awayTeam": {
                "teamNameCH": "哥連泰斯",
                "teamNameEN": "Corinthians"
            },
            "isESOffer": true,
            "tournament": {
                "tournamentNameCH": "南美球會盃",
                "tournamentNameEN": "South American Cup"
            },
            "liveEvent": {
                "hasLiveInfo": true
            },
            "anyInplaySelling": "1"
        },
        {
            "matchTime": "2024-04-24T10:00:00.000+08:00",
            "frontEndId": "FB5393",
            "homeTeam": {
                "teamNameCH": "哥倫比亞女足U20",
                "teamNameEN": "Colombia Women U20"
            },
            "awayTeam": {
                "teamNameCH": "秘魯女足U20",
                "teamNameEN": "Peru Women U20"
            },
            "isESOffer": true,
            "tournament": {
                "tournamentNameCH": "國際賽",
                "tournamentNameEN": "International Matches"
            },
            "liveEvent": {
                "hasLiveInfo": false
            },
            "anyInplaySelling": "-1"
        },
        {
            "matchTime": "2024-04-24T10:00:00.000+08:00",
            "frontEndId": "FB5334",
            "homeTeam": {
                "teamNameCH": "青年體育會",
                "teamNameEN": "Atletico Junior"
            },
            "awayTeam": {
                "teamNameCH": "利加大學",
                "teamNameEN": "LDU Quito"
            },
            "isESOffer": true,
            "tournament": {
                "tournamentNameCH": "南美自由盃",
                "tournamentNameEN": "Copa Libertadores"
            },
            "liveEvent": {
                "hasLiveInfo": true
            },
            "anyInplaySelling": "1"
        },
        {
            "matchTime": "2024-04-24T10:00:00.000+08:00",
            "frontEndId": "FB5352",
            "homeTeam": {
                "teamNameCH": "巴耶杜帕爾聯",
                "teamNameEN": "Alianza Valledupar"
            },
            "awayTeam": {
                "teamNameCH": "基多天主教大學",
                "teamNameEN": "Universidad Catolica Quito"
            },
            "isESOffer": true,
            "tournament": {
                "tournamentNameCH": "南美球會盃",
                "tournamentNameEN": "South American Cup"
            },
            "liveEvent": {
                "hasLiveInfo": true
            },
            "anyInplaySelling": "1"
        },
        {
            "matchTime": "2024-04-24T10:15:00.000+08:00",
            "frontEndId": "FB5363",
            "homeTeam": {
                "teamNameCH": "CF 阿美利加",
                "teamNameEN": "CF America"
            },
            "awayTeam": {
                "teamNameCH": "帕丘卡",
                "teamNameEN": "Pachuca"
            },
            "isESOffer": true,
            "tournament": {
                "tournamentNameCH": "中北美洲冠軍盃",
                "tournamentNameEN": "Central and North American Cup"
            },
            "liveEvent": {
                "hasLiveInfo": true
            },
            "anyInplaySelling": "1"
        },
        {
            "matchTime": "2024-04-24T18:00:00.000+08:00",
            "frontEndId": "FB5302",
            "homeTeam": {
                "teamNameCH": "橫濱水手",
                "teamNameEN": "Yokohama F.Marinos"
            },
            "awayTeam": {
                "teamNameCH": "蔚山HD",
                "teamNameEN": "Ulsan HD"
            },
            "isESOffer": false,
            "tournament": {
                "tournamentNameCH": "亞洲聯賽冠軍盃",
                "tournamentNameEN": "Asian Champions League"
            },
            "liveEvent": {
                "hasLiveInfo": true
            },
            "anyInplaySelling": "1"
        },
        {
            "matchTime": "2024-04-24T18:00:00.000+08:00",
            "frontEndId": "FB5309",
            "homeTeam": {
                "teamNameCH": "秋田藍閃電",
                "teamNameEN": "Blaublitz Akita"
            },
            "awayTeam": {
                "teamNameCH": "湘南比馬",
                "teamNameEN": "Shonan Bellmare"
            },
            "isESOffer": false,
            "tournament": {
                "tournamentNameCH": "日本聯賽盃",
                "tournamentNameEN": "Japanese League Cup"
            },
            "liveEvent": {
                "hasLiveInfo": false
            },
            "anyInplaySelling": "1"
        },
        {
            "matchTime": "2024-04-24T18:00:00.000+08:00",
            "frontEndId": "FB5313",
            "homeTeam": {
                "teamNameCH": "FC琉球",
                "teamNameEN": "FC Ryukyu"
            },
            "awayTeam": {
                "teamNameCH": "大阪飛腳",
                "teamNameEN": "Gamba Osaka"
            },
            "isESOffer": false,
            "tournament": {
                "tournamentNameCH": "日本聯賽盃",
                "tournamentNameEN": "Japanese League Cup"
            },
            "liveEvent": {
                "hasLiveInfo": false
            },
            "anyInplaySelling": "1"
        },
        {
            "matchTime": "2024-04-24T18:00:00.000+08:00",
            "frontEndId": "FB5308",
            "homeTeam": {
                "teamNameCH": "岡山綠雉",
                "teamNameEN": "Fagiano Okayama"
            },
            "awayTeam": {
                "teamNameCH": "FC橫濱",
                "teamNameEN": "FC Yokohama"
            },
            "isESOffer": false,
            "tournament": {
                "tournamentNameCH": "日本聯賽盃",
                "tournamentNameEN": "Japanese League Cup"
            },
            "liveEvent": {
                "hasLiveInfo": false
            },
            "anyInplaySelling": "1"
        },
        {
            "matchTime": "2024-04-24T18:00:00.000+08:00",
            "frontEndId": "FB5314",
            "homeTeam": {
                "teamNameCH": "富山勝利",
                "teamNameEN": "Kataller Toyama"
            },
            "awayTeam": {
                "teamNameCH": "清水心跳",
                "teamNameEN": "Shimizu S-Pulse"
            },
            "isESOffer": false,
            "tournament": {
                "tournamentNameCH": "日本聯賽盃",
                "tournamentNameEN": "Japanese League Cup"
            },
            "liveEvent": {
                "hasLiveInfo": false
            },
            "anyInplaySelling": "1"
        },
        {
            "matchTime": "2024-04-24T18:00:00.000+08:00",
            "frontEndId": "FB5310",
            "homeTeam": {
                "teamNameCH": "長野帕塞羅",
                "teamNameEN": "Nagano Parceiro"
            },
            "awayTeam": {
                "teamNameCH": "京都不死鳥",
                "teamNameEN": "Kyoto Sanga"
            },
            "isESOffer": false,
            "tournament": {
                "tournamentNameCH": "日本聯賽盃",
                "tournamentNameEN": "Japanese League Cup"
            },
            "liveEvent": {
                "hasLiveInfo": false
            },
            "anyInplaySelling": "1"
        },
        {
            "matchTime": "2024-04-24T18:00:00.000+08:00",
            "frontEndId": "FB5359",
            "homeTeam": {
                "teamNameCH": "奈良俱樂部",
                "teamNameEN": "Nara Club"
            },
            "awayTeam": {
                "teamNameCH": "廣島三箭",
                "teamNameEN": "Sanfrecce Hiroshima"
            },
            "isESOffer": false,
            "tournament": {
                "tournamentNameCH": "日本聯賽盃",
                "tournamentNameEN": "Japanese League Cup"
            },
            "liveEvent": {
                "hasLiveInfo": false
            },
            "anyInplaySelling": "1"
        },
        {
            "matchTime": "2024-04-24T18:00:00.000+08:00",
            "frontEndId": "FB5312",
            "homeTeam": {
                "teamNameCH": "熊本羅亞素",
                "teamNameEN": "Roasso Kumamoto"
            },
            "awayTeam": {
                "teamNameCH": "鳥棲砂岩",
                "teamNameEN": "Sagan Tosu"
            },
            "isESOffer": false,
            "tournament": {
                "tournamentNameCH": "日本聯賽盃",
                "tournamentNameEN": "Japanese League Cup"
            },
            "liveEvent": {
                "hasLiveInfo": false
            },
            "anyInplaySelling": "1"
        },
        {
            "matchTime": "2024-04-24T18:00:00.000+08:00",
            "frontEndId": "FB5311",
            "homeTeam": {
                "teamNameCH": "群馬草津溫泉",
                "teamNameEN": "Thespakusatsu Gunma"
            },
            "awayTeam": {
                "teamNameCH": "柏雷素爾",
                "teamNameEN": "Kashiwa Reysol"
            },
            "isESOffer": false,
            "tournament": {
                "tournamentNameCH": "日本聯賽盃",
                "tournamentNameEN": "Japanese League Cup"
            },
            "liveEvent": {
                "hasLiveInfo": false
            },
            "anyInplaySelling": "1"
        },
        {
            "matchTime": "2024-04-24T18:30:00.000+08:00",
            "frontEndId": "FB5365",
            "homeTeam": {
                "teamNameCH": "鳥取飛翔",
                "teamNameEN": "Gainare Tottori"
            },
            "awayTeam": {
                "teamNameCH": "浦和紅鑽",
                "teamNameEN": "Urawa Reds"
            },
            "isESOffer": false,
            "tournament": {
                "tournamentNameCH": "日本聯賽盃",
                "tournamentNameEN": "Japanese League Cup"
            },
            "liveEvent": {
                "hasLiveInfo": false
            },
            "anyInplaySelling": "1"
        },
        {
            "matchTime": "2024-04-24T21:00:00.000+08:00",
            "frontEndId": "FB5366",
            "homeTeam": {
                "teamNameCH": "FC奧倫堡",
                "teamNameEN": "FC Orenburg"
            },
            "awayTeam": {
                "teamNameCH": "莫斯科戴拿模",
                "teamNameEN": "Dinamo Moscow"
            },
            "isESOffer": false,
            "tournament": {
                "tournamentNameCH": "俄羅斯超級聯賽",
                "tournamentNameEN": "Russian Premier"
            },
            "liveEvent": {
                "hasLiveInfo": true
            },
            "anyInplaySelling": "-1"
        },
        {
            "matchTime": "2024-04-24T23:15:00.000+08:00",
            "frontEndId": "FB5368",
            "homeTeam": {
                "teamNameCH": "FC下諾夫哥羅德",
                "teamNameEN": "FC Nizhny Novgorod"
            },
            "awayTeam": {
                "teamNameCH": "莫斯科火車頭",
                "teamNameEN": "Lokomotiv Moscow"
            },
            "isESOffer": true,
            "tournament": {
                "tournamentNameCH": "俄羅斯超級聯賽",
                "tournamentNameEN": "Russian Premier"
            },
            "liveEvent": {
                "hasLiveInfo": true
            },
            "anyInplaySelling": "-1"
        },
        {
            "matchTime": "2024-04-25T00:00:00.000+08:00",
            "frontEndId": "FB5382",
            "homeTeam": {
                "teamNameCH": "施拿祖基",
                "teamNameEN": "SJK Seinajoki"
            },
            "awayTeam": {
                "teamNameCH": "赫爾辛基",
                "teamNameEN": "HJK Helsinki"
            },
            "isESOffer": true,
            "tournament": {
                "tournamentNameCH": "芬蘭超級聯賽",
                "tournamentNameEN": "Finnish Division 1"
            },
            "liveEvent": {
                "hasLiveInfo": true
            },
            "anyInplaySelling": "1"
        },
        {
            "matchTime": "2024-04-25T00:45:00.000+08:00",
            "frontEndId": "FB5322",
            "homeTeam": {
                "teamNameCH": "川迪",
                "teamNameEN": "Twente"
            },
            "awayTeam": {
                "teamNameCH": "阿梅爾城",
                "teamNameEN": "Almere City"
            },
            "isESOffer": true,
            "tournament": {
                "tournamentNameCH": "荷蘭甲組聯賽",
                "tournamentNameEN": "Dutch Division 1"
            },
            "liveEvent": {
                "hasLiveInfo": true
            },
            "anyInplaySelling": "1"
        },
        {
            "matchTime": "2024-04-25T01:00:00.000+08:00",
            "frontEndId": "FB5318",
            "homeTeam": {
                "teamNameCH": "羅連安特",
                "teamNameEN": "Lorient"
            },
            "awayTeam": {
                "teamNameCH": "巴黎聖日耳門",
                "teamNameEN": "Paris Saint Germain"
            },
            "isESOffer": true,
            "tournament": {
                "tournamentNameCH": "法國甲組聯賽",
                "tournamentNameEN": "French Division 1"
            },
            "liveEvent": {
                "hasLiveInfo": true
            },
            "anyInplaySelling": "1"
        },
        {
            "matchTime": "2024-04-25T01:00:00.000+08:00",
            "frontEndId": "FB5316",
            "homeTeam": {
                "teamNameCH": "AIK蘇納",
                "teamNameEN": "AIK Solna"
            },
            "awayTeam": {
                "teamNameCH": "華納莫",
                "teamNameEN": "Varnamo"
            },
            "isESOffer": true,
            "tournament": {
                "tournamentNameCH": "瑞典超級聯賽",
                "tournamentNameEN": "Swedish Division 1"
            },
            "liveEvent": {
                "hasLiveInfo": true
            },
            "anyInplaySelling": "-1"
        },
        {
            "matchTime": "2024-04-25T01:00:00.000+08:00",
            "frontEndId": "FB5320",
            "homeTeam": {
                "teamNameCH": "布洛馬波卡納",
                "teamNameEN": "Brommapojkarna"
            },
            "awayTeam": {
                "teamNameCH": "天狼星",
                "teamNameEN": "Sirius"
            },
            "isESOffer": true,
            "tournament": {
                "tournamentNameCH": "瑞典超級聯賽",
                "tournamentNameEN": "Swedish Division 1"
            },
            "liveEvent": {
                "hasLiveInfo": true
            },
            "anyInplaySelling": "-1"
        },
        {
            "matchTime": "2024-04-25T01:00:00.000+08:00",
            "frontEndId": "FB5319",
            "homeTeam": {
                "teamNameCH": "哥登堡",
                "teamNameEN": "Goteborg"
            },
            "awayTeam": {
                "teamNameCH": "赫根",
                "teamNameEN": "Hacken"
            },
            "isESOffer": true,
            "tournament": {
                "tournamentNameCH": "瑞典超級聯賽",
                "tournamentNameEN": "Swedish Division 1"
            },
            "liveEvent": {
                "hasLiveInfo": true
            },
            "anyInplaySelling": "-1"
        },
        {
            "matchTime": "2024-04-25T01:30:00.000+08:00",
            "frontEndId": "FB5367",
            "homeTeam": {
                "teamNameCH": "卡斯洛達",
                "teamNameEN": "FK Krasnodar"
            },
            "awayTeam": {
                "teamNameCH": "巴爾迪卡",
                "teamNameEN": "Baltika Kaliningrad"
            },
            "isESOffer": true,
            "tournament": {
                "tournamentNameCH": "俄羅斯超級聯賽",
                "tournamentNameEN": "Russian Premier"
            },
            "liveEvent": {
                "hasLiveInfo": true
            },
            "anyInplaySelling": "-1"
        },
        {
            "matchTime": "2024-04-25T01:30:00.000+08:00",
            "frontEndId": "FB5369",
            "homeTeam": {
                "teamNameCH": "辛尼特",
                "teamNameEN": "Zenit St. Petersburg"
            },
            "awayTeam": {
                "teamNameCH": "魯賓卡山",
                "teamNameEN": "Rubin Kazan"
            },
            "isESOffer": true,
            "tournament": {
                "tournamentNameCH": "俄羅斯超級聯賽",
                "tournamentNameEN": "Russian Premier"
            },
            "liveEvent": {
                "hasLiveInfo": true
            },
            "anyInplaySelling": "-1"
        },
        {
            "matchTime": "2024-04-25T02:30:00.000+08:00",
            "frontEndId": "FB5325",
            "homeTeam": {
                "teamNameCH": "安德列治",
                "teamNameEN": "Anderlecht"
            },
            "awayTeam": {
                "teamNameCH": "布魯日舒高",
                "teamNameEN": "Cercle Bruges"
            },
            "isESOffer": true,
            "tournament": {
                "tournamentNameCH": "比利時甲組聯賽",
                "tournamentNameEN": "Belgian Division 1"
            },
            "liveEvent": {
                "hasLiveInfo": true
            },
            "anyInplaySelling": "-1"
        },
        {
            "matchTime": "2024-04-25T02:30:00.000+08:00",
            "frontEndId": "FB5326",
            "homeTeam": {
                "teamNameCH": "布魯日",
                "teamNameEN": "Bruges"
            },
            "awayTeam": {
                "teamNameCH": "亨克",
                "teamNameEN": "Genk"
            },
            "isESOffer": true,
            "tournament": {
                "tournamentNameCH": "比利時甲組聯賽",
                "tournamentNameEN": "Belgian Division 1"
            },
            "liveEvent": {
                "hasLiveInfo": true
            },
            "anyInplaySelling": "-1"
        },
        {
            "matchTime": "2024-04-25T02:45:00.000+08:00",
            "frontEndId": "FB5344",
            "homeTeam": {
                "teamNameCH": "狼隊",
                "teamNameEN": "Wolves"
            },
            "awayTeam": {
                "teamNameCH": "般尼茅夫",
                "teamNameEN": "Bournemouth"
            },
            "isESOffer": true,
            "tournament": {
                "tournamentNameCH": "英格蘭超級聯賽",
                "tournamentNameEN": "Eng Premier"
            },
            "liveEvent": {
                "hasLiveInfo": true
            },
            "anyInplaySelling": "1"
        },
        {
            "matchTime": "2024-04-25T02:45:00.000+08:00",
            "frontEndId": "FB5360",
            "homeTeam": {
                "teamNameCH": "高雲地利",
                "teamNameEN": "Coventry"
            },
            "awayTeam": {
                "teamNameCH": "侯城",
                "teamNameEN": "Hull City"
            },
            "isESOffer": true,
            "tournament": {
                "tournamentNameCH": "英格蘭冠軍聯賽",
                "tournamentNameEN": "Eng Championship"
            },
            "liveEvent": {
                "hasLiveInfo": true
            },
            "anyInplaySelling": "1"
        },
        {
            "matchTime": "2024-04-25T03:00:00.000+08:00",
            "frontEndId": "FB5345",
            "homeTeam": {
                "teamNameCH": "曼聯",
                "teamNameEN": "Manchester Utd"
            },
            "awayTeam": {
                "teamNameCH": "錫菲聯",
                "teamNameEN": "Sheff Utd"
            },
            "isESOffer": true,
            "tournament": {
                "tournamentNameCH": "英格蘭超級聯賽",
                "tournamentNameEN": "Eng Premier"
            },
            "liveEvent": {
                "hasLiveInfo": true
            },
            "anyInplaySelling": "1"
        },
        {
            "matchTime": "2024-04-25T03:00:00.000+08:00",
            "frontEndId": "FB5346",
            "homeTeam": {
                "teamNameCH": "愛華頓",
                "teamNameEN": "Everton"
            },
            "awayTeam": {
                "teamNameCH": "利物浦",
                "teamNameEN": "Liverpool"
            },
            "isESOffer": true,
            "tournament": {
                "tournamentNameCH": "英格蘭超級聯賽",
                "tournamentNameEN": "Eng Premier"
            },
            "liveEvent": {
                "hasLiveInfo": true
            },
            "anyInplaySelling": "1"
        },
        {
            "matchTime": "2024-04-25T03:00:00.000+08:00",
            "frontEndId": "FB5343",
            "homeTeam": {
                "teamNameCH": "水晶宮",
                "teamNameEN": "Crystal Palace"
            },
            "awayTeam": {
                "teamNameCH": "紐卡素",
                "teamNameEN": "Newcastle"
            },
            "isESOffer": true,
            "tournament": {
                "tournamentNameCH": "英格蘭超級聯賽",
                "tournamentNameEN": "Eng Premier"
            },
            "liveEvent": {
                "hasLiveInfo": true
            },
            "anyInplaySelling": "1"
        },
        {
            "matchTime": "2024-04-25T03:00:00.000+08:00",
            "frontEndId": "FB5306",
            "homeTeam": {
                "teamNameCH": "阿特蘭大",
                "teamNameEN": "Atalanta"
            },
            "awayTeam": {
                "teamNameCH": "費倫天拿",
                "teamNameEN": "Fiorentina"
            },
            "isESOffer": true,
            "tournament": {
                "tournamentNameCH": "意大利盃",
                "tournamentNameEN": "Italian Cup"
            },
            "liveEvent": {
                "hasLiveInfo": true
            },
            "anyInplaySelling": "1"
        },
        {
            "matchTime": "2024-04-25T03:00:00.000+08:00",
            "frontEndId": "FB5321",
            "homeTeam": {
                "teamNameCH": "馬賽",
                "teamNameEN": "Marseille"
            },
            "awayTeam": {
                "teamNameCH": "尼斯",
                "teamNameEN": "Nice"
            },
            "isESOffer": true,
            "tournament": {
                "tournamentNameCH": "法國甲組聯賽",
                "tournamentNameEN": "French Division 1"
            },
            "liveEvent": {
                "hasLiveInfo": true
            },
            "anyInplaySelling": "1"
        },
        {
            "matchTime": "2024-04-25T03:00:00.000+08:00",
            "frontEndId": "FB5317",
            "homeTeam": {
                "teamNameCH": "摩納哥",
                "teamNameEN": "Monaco"
            },
            "awayTeam": {
                "teamNameCH": "里爾",
                "teamNameEN": "Lille"
            },
            "isESOffer": true,
            "tournament": {
                "tournamentNameCH": "法國甲組聯賽",
                "tournamentNameEN": "French Division 1"
            },
            "liveEvent": {
                "hasLiveInfo": true
            },
            "anyInplaySelling": "-1"
        },
        {
            "matchTime": "2024-04-25T03:00:00.000+08:00",
            "frontEndId": "FB5348",
            "homeTeam": {
                "teamNameCH": "阿積士",
                "teamNameEN": "Ajax"
            },
            "awayTeam": {
                "teamNameCH": "精英隊",
                "teamNameEN": "Excelsior"
            },
            "isESOffer": true,
            "tournament": {
                "tournamentNameCH": "荷蘭甲組聯賽",
                "tournamentNameEN": "Dutch Division 1"
            },
            "liveEvent": {
                "hasLiveInfo": true
            },
            "anyInplaySelling": "-1"
        },
        {
            "matchTime": "2024-04-25T06:00:00.000+08:00",
            "frontEndId": "FB5379",
            "homeTeam": {
                "teamNameCH": "侯治柏度",
                "teamNameEN": "Huachipato"
            },
            "awayTeam": {
                "teamNameCH": "強者",
                "teamNameEN": "The Strongest"
            },
            "isESOffer": true,
            "tournament": {
                "tournamentNameCH": "南美自由盃",
                "tournamentNameEN": "Copa Libertadores"
            },
            "liveEvent": {
                "hasLiveInfo": true
            },
            "anyInplaySelling": "1"
        },
        {
            "matchTime": "2024-04-25T06:00:00.000+08:00",
            "frontEndId": "FB5371",
            "homeTeam": {
                "teamNameCH": "保地花高",
                "teamNameEN": "Botafogo"
            },
            "awayTeam": {
                "teamNameCH": "秘魯體育大學",
                "teamNameEN": "Universitario Deportes"
            },
            "isESOffer": true,
            "tournament": {
                "tournamentNameCH": "南美自由盃",
                "tournamentNameEN": "Copa Libertadores"
            },
            "liveEvent": {
                "hasLiveInfo": true
            },
            "anyInplaySelling": "-1"
        },
        {
            "matchTime": "2024-04-25T06:00:00.000+08:00",
            "frontEndId": "FB5377",
            "homeTeam": {
                "teamNameCH": "蒙特維多國民隊",
                "teamNameEN": "Montevideo Nacional"
            },
            "awayTeam": {
                "teamNameCH": "塔奇拉",
                "teamNameEN": "Deportivo Tachira"
            },
            "isESOffer": true,
            "tournament": {
                "tournamentNameCH": "南美自由盃",
                "tournamentNameEN": "Copa Libertadores"
            },
            "liveEvent": {
                "hasLiveInfo": true
            },
            "anyInplaySelling": "-1"
        },
        {
            "matchTime": "2024-04-25T06:00:00.000+08:00",
            "frontEndId": "FB5380",
            "homeTeam": {
                "teamNameCH": "哥甘保",
                "teamNameEN": "Coquimbo Unido"
            },
            "awayTeam": {
                "teamNameCH": "競賽會",
                "teamNameEN": "Racing Club"
            },
            "isESOffer": true,
            "tournament": {
                "tournamentNameCH": "南美球會盃",
                "tournamentNameEN": "South American Cup"
            },
            "liveEvent": {
                "hasLiveInfo": true
            },
            "anyInplaySelling": "-1"
        },
        {
            "matchTime": "2024-04-25T06:00:00.000+08:00",
            "frontEndId": "FB5381",
            "homeTeam": {
                "teamNameCH": "達奴比奧",
                "teamNameEN": "Danubio"
            },
            "awayTeam": {
                "teamNameCH": "帕拉尼恩斯",
                "teamNameEN": "Athletico Paranaense"
            },
            "isESOffer": true,
            "tournament": {
                "tournamentNameCH": "南美球會盃",
                "tournamentNameEN": "South American Cup"
            },
            "liveEvent": {
                "hasLiveInfo": true
            },
            "anyInplaySelling": "-1"
        },
        {
            "matchTime": "2024-04-25T08:00:00.000+08:00",
            "frontEndId": "FB5383",
            "homeTeam": {
                "teamNameCH": "利伯泰迪",
                "teamNameEN": "Libertad"
            },
            "awayTeam": {
                "teamNameCH": "河床",
                "teamNameEN": "River Plate"
            },
            "isESOffer": true,
            "tournament": {
                "tournamentNameCH": "南美自由盃",
                "tournamentNameEN": "Copa Libertadores"
            },
            "liveEvent": {
                "hasLiveInfo": true
            },
            "anyInplaySelling": "-1"
        },
        {
            "matchTime": "2024-04-25T08:00:00.000+08:00",
            "frontEndId": "FB5372",
            "homeTeam": {
                "teamNameCH": "巴拉干天奴紅牛",
                "teamNameEN": "RB Bragantino"
            },
            "awayTeam": {
                "teamNameCH": "路昆奴",
                "teamNameEN": "Sportivo Luqueno"
            },
            "isESOffer": true,
            "tournament": {
                "tournamentNameCH": "南美球會盃",
                "tournamentNameEN": "South American Cup"
            },
            "liveEvent": {
                "hasLiveInfo": true
            },
            "anyInplaySelling": "-1"
        },
        {
            "matchTime": "2024-04-25T08:15:00.000+08:00",
            "frontEndId": "FB5364",
            "homeTeam": {
                "teamNameCH": "哥倫布機員",
                "teamNameEN": "Columbus Crew"
            },
            "awayTeam": {
                "teamNameCH": "蒙特雷",
                "teamNameEN": "Monterrey"
            },
            "isESOffer": true,
            "tournament": {
                "tournamentNameCH": "中北美洲冠軍盃",
                "tournamentNameEN": "Central and North American Cup"
            },
            "liveEvent": {
                "hasLiveInfo": true
            },
            "anyInplaySelling": "1"
        },
        {
            "matchTime": "2024-04-25T08:30:00.000+08:00",
            "frontEndId": "FB5378",
            "homeTeam": {
                "teamNameCH": "迪華利獨立隊",
                "teamNameEN": "Independiente del Valle"
            },
            "awayTeam": {
                "teamNameCH": "彭美拉斯",
                "teamNameEN": "Palmeiras"
            },
            "isESOffer": true,
            "tournament": {
                "tournamentNameCH": "南美自由盃",
                "tournamentNameEN": "Copa Libertadores"
            },
            "liveEvent": {
                "hasLiveInfo": true
            },
            "anyInplaySelling": "1"
        },
        {
            "matchTime": "2024-04-25T08:30:00.000+08:00",
            "frontEndId": "FB5385",
            "homeTeam": {
                "teamNameCH": "玻利瓦爾",
                "teamNameEN": "Bolivar"
            },
            "awayTeam": {
                "teamNameCH": "法林明高",
                "teamNameEN": "Flamengo"
            },
            "isESOffer": true,
            "tournament": {
                "tournamentNameCH": "南美自由盃",
                "tournamentNameEN": "Copa Libertadores"
            },
            "liveEvent": {
                "hasLiveInfo": true
            },
            "anyInplaySelling": "-1"
        },
        {
            "matchTime": "2024-04-25T08:30:00.000+08:00",
            "frontEndId": "FB5384",
            "homeTeam": {
                "teamNameCH": "皇家杜馬耶保",
                "teamNameEN": "Real Tomayapo"
            },
            "awayTeam": {
                "teamNameCH": "貝格拉諾",
                "teamNameEN": "Belgrano"
            },
            "isESOffer": true,
            "tournament": {
                "tournamentNameCH": "南美球會盃",
                "tournamentNameEN": "South American Cup"
            },
            "liveEvent": {
                "hasLiveInfo": true
            },
            "anyInplaySelling": "-1"
        },
        {
            "matchTime": "2024-04-25T10:00:00.000+08:00",
            "frontEndId": "FB5386",
            "homeTeam": {
                "teamNameCH": "祖利亞諾",
                "teamNameEN": "Deportivo Rayo Zuliano"
            },
            "awayTeam": {
                "teamNameCH": "艾美利亞諾",
                "teamNameEN": "Sportivo Ameliano"
            },
            "isESOffer": true,
            "tournament": {
                "tournamentNameCH": "南美球會盃",
                "tournamentNameEN": "South American Cup"
            },
            "liveEvent": {
                "hasLiveInfo": true
            },
            "anyInplaySelling": "1"
        },
        {
            "matchTime": "2024-04-25T21:00:00.000+08:00",
            "frontEndId": "FB5387",
            "homeTeam": {
                "teamNameCH": "烏拉爾",
                "teamNameEN": "Ural Yekaterinburg"
            },
            "awayTeam": {
                "teamNameCH": "羅斯托夫",
                "teamNameEN": "Rostov"
            },
            "isESOffer": true,
            "tournament": {
                "tournamentNameCH": "俄羅斯超級聯賽",
                "tournamentNameEN": "Russian Premier"
            },
            "liveEvent": {
                "hasLiveInfo": true
            },
            "anyInplaySelling": "-1"
        },
        {
            "matchTime": "2024-04-25T22:00:00.000+08:00",
            "frontEndId": "FB5394",
            "homeTeam": {
                "teamNameCH": "卡塔爾U23",
                "teamNameEN": "Qatar U23"
            },
            "awayTeam": {
                "teamNameCH": "日本U23",
                "teamNameEN": "Japan U23"
            },
            "isESOffer": true,
            "tournament": {
                "tournamentNameCH": "U23亞洲盃",
                "tournamentNameEN": "U23 Asian Cup"
            },
            "liveEvent": {
                "hasLiveInfo": true
            },
            "anyInplaySelling": "1"
        },
        {
            "matchTime": "2024-04-25T23:15:00.000+08:00",
            "frontEndId": "FB5388",
            "homeTeam": {
                "teamNameCH": "法高爾佛羅內什",
                "teamNameEN": "Fakel Voronezh"
            },
            "awayTeam": {
                "teamNameCH": "森馬拉",
                "teamNameEN": "Krylya Sovetov Samara"
            },
            "isESOffer": true,
            "tournament": {
                "tournamentNameCH": "俄羅斯超級聯賽",
                "tournamentNameEN": "Russian Premier"
            },
            "liveEvent": {
                "hasLiveInfo": true
            },
            "anyInplaySelling": "-1"
        },
        {
            "matchTime": "2024-04-26T00:45:00.000+08:00",
            "frontEndId": "FB5373",
            "homeTeam": {
                "teamNameCH": "海倫芬",
                "teamNameEN": "Heerenveen"
            },
            "awayTeam": {
                "teamNameCH": "燕豪芬",
                "teamNameEN": "PSV Eindhoven"
            },
            "isESOffer": true,
            "tournament": {
                "tournamentNameCH": "荷蘭甲組聯賽",
                "tournamentNameEN": "Dutch Division 1"
            },
            "liveEvent": {
                "hasLiveInfo": true
            },
            "anyInplaySelling": "1"
        },
        {
            "matchTime": "2024-04-26T01:00:00.000+08:00",
            "frontEndId": "FB5375",
            "homeTeam": {
                "teamNameCH": "諾高平",
                "teamNameEN": "Norrkoping"
            },
            "awayTeam": {
                "teamNameCH": "艾夫斯堡",
                "teamNameEN": "Elfsborg"
            },
            "isESOffer": true,
            "tournament": {
                "tournamentNameCH": "瑞典超級聯賽",
                "tournamentNameEN": "Swedish Division 1"
            },
            "liveEvent": {
                "hasLiveInfo": true
            },
            "anyInplaySelling": "1"
        },
        {
            "matchTime": "2024-04-26T01:00:00.000+08:00",
            "frontEndId": "FB5328",
            "homeTeam": {
                "teamNameCH": "佐加頓斯",
                "teamNameEN": "Djurgardens"
            },
            "awayTeam": {
                "teamNameCH": "馬模",
                "teamNameEN": "Malmo"
            },
            "isESOffer": true,
            "tournament": {
                "tournamentNameCH": "瑞典超級聯賽",
                "tournamentNameEN": "Swedish Division 1"
            },
            "liveEvent": {
                "hasLiveInfo": true
            },
            "anyInplaySelling": "-1"
        },
        {
            "matchTime": "2024-04-26T01:00:00.000+08:00",
            "frontEndId": "FB5332",
            "homeTeam": {
                "teamNameCH": "咸史達斯",
                "teamNameEN": "Halmstads"
            },
            "awayTeam": {
                "teamNameCH": "哈馬比",
                "teamNameEN": "Hammarby"
            },
            "isESOffer": true,
            "tournament": {
                "tournamentNameCH": "瑞典超級聯賽",
                "tournamentNameEN": "Swedish Division 1"
            },
            "liveEvent": {
                "hasLiveInfo": true
            },
            "anyInplaySelling": "-1"
        },
        {
            "matchTime": "2024-04-26T01:00:00.000+08:00",
            "frontEndId": "FB5374",
            "homeTeam": {
                "teamNameCH": "卡爾馬",
                "teamNameEN": "Kalmar"
            },
            "awayTeam": {
                "teamNameCH": "加爾斯",
                "teamNameEN": "GAIS"
            },
            "isESOffer": true,
            "tournament": {
                "tournamentNameCH": "瑞典超級聯賽",
                "tournamentNameEN": "Swedish Division 1"
            },
            "liveEvent": {
                "hasLiveInfo": true
            },
            "anyInplaySelling": "-1"
        },
        {
            "matchTime": "2024-04-26T01:00:00.000+08:00",
            "frontEndId": "FB5329",
            "homeTeam": {
                "teamNameCH": "華斯特拉斯",
                "teamNameEN": "Vasteras SK"
            },
            "awayTeam": {
                "teamNameCH": "米贊比",
                "teamNameEN": "Mjallby"
            },
            "isESOffer": true,
            "tournament": {
                "tournamentNameCH": "瑞典超級聯賽",
                "tournamentNameEN": "Swedish Division 1"
            },
            "liveEvent": {
                "hasLiveInfo": true
            },
            "anyInplaySelling": "-1"
        },
        {
            "matchTime": "2024-04-26T01:30:00.000+08:00",
            "frontEndId": "FB5395",
            "homeTeam": {
                "teamNameCH": "南韓U23",
                "teamNameEN": "Korea Republic U23"
            },
            "awayTeam": {
                "teamNameCH": "印尼U23",
                "teamNameEN": "Indonesia U23"
            },
            "isESOffer": true,
            "tournament": {
                "tournamentNameCH": "U23亞洲盃",
                "tournamentNameEN": "U23 Asian Cup"
            },
            "liveEvent": {
                "hasLiveInfo": true
            },
            "anyInplaySelling": "1"
        },
        {
            "matchTime": "2024-04-26T01:30:00.000+08:00",
            "frontEndId": "FB5390",
            "homeTeam": {
                "teamNameCH": "莫斯科中央陸軍",
                "teamNameEN": "CSKA Moscow"
            },
            "awayTeam": {
                "teamNameCH": "莫斯科斯巴達",
                "teamNameEN": "Spartak Moscow"
            },
            "isESOffer": true,
            "tournament": {
                "tournamentNameCH": "俄羅斯超級聯賽",
                "tournamentNameEN": "Russian Premier"
            },
            "liveEvent": {
                "hasLiveInfo": true
            },
            "anyInplaySelling": "-1"
        },
        {
            "matchTime": "2024-04-26T01:30:00.000+08:00",
            "frontEndId": "FB5389",
            "homeTeam": {
                "teamNameCH": "艾卡馬特",
                "teamNameEN": "Akhmat Grozny"
            },
            "awayTeam": {
                "teamNameCH": "PFC索契",
                "teamNameEN": "PFC Sochi"
            },
            "isESOffer": true,
            "tournament": {
                "tournamentNameCH": "俄羅斯超級聯賽",
                "tournamentNameEN": "Russian Premier"
            },
            "liveEvent": {
                "hasLiveInfo": true
            },
            "anyInplaySelling": "-1"
        },
        {
            "matchTime": "2024-04-26T02:30:00.000+08:00",
            "frontEndId": "FB5330",
            "homeTeam": {
                "teamNameCH": "安特衛普",
                "teamNameEN": "Antwerp"
            },
            "awayTeam": {
                "teamNameCH": "聖基萊斯聯",
                "teamNameEN": "Union Saint Gilloise"
            },
            "isESOffer": true,
            "tournament": {
                "tournamentNameCH": "比利時甲組聯賽",
                "tournamentNameEN": "Belgian Division 1"
            },
            "liveEvent": {
                "hasLiveInfo": true
            },
            "anyInplaySelling": "-1"
        },
        {
            "matchTime": "2024-04-26T03:00:00.000+08:00",
            "frontEndId": "FB5342",
            "homeTeam": {
                "teamNameCH": "白禮頓",
                "teamNameEN": "Brighton"
            },
            "awayTeam": {
                "teamNameCH": "曼城",
                "teamNameEN": "Manchester City"
            },
            "isESOffer": true,
            "tournament": {
                "tournamentNameCH": "英格蘭超級聯賽",
                "tournamentNameEN": "Eng Premier"
            },
            "liveEvent": {
                "hasLiveInfo": true
            },
            "anyInplaySelling": "1"
        },
        {
            "matchTime": "2024-04-26T03:00:00.000+08:00",
            "frontEndId": "FB5376",
            "homeTeam": {
                "teamNameCH": "伊高斯",
                "teamNameEN": "Go Ahead Eagles"
            },
            "awayTeam": {
                "teamNameCH": "飛燕諾",
                "teamNameEN": "Feyenoord"
            },
            "isESOffer": true,
            "tournament": {
                "tournamentNameCH": "荷蘭甲組聯賽",
                "tournamentNameEN": "Dutch Division 1"
            },
            "liveEvent": {
                "hasLiveInfo": true
            },
            "anyInplaySelling": "1"
        }
    ]
}